pynovaposhta-0.2.0.dist-info/dependency_links.txt
pynovaposhta-0.2.0.dist-info/entry_points.txt
pynovaposhta-0.2.0.dist-info/METADATA
pynovaposhta-0.2.0.dist-info/top_level.txt
pynovaposhta-0.2.0.dist-info/WHEEL
novaposhta/abstract.py
novaposhta/client.py
novaposhta/const.py
novaposhta/exceptions.py
novaposhta/__init__.py
novaposhta/models/abstract.py
novaposhta/models/additional_service_general.py
novaposhta/models/addresses.py
novaposhta/models/common.py
novaposhta/models/counterparties.py
novaposhta/models/internet_documents.py
novaposhta/models/scan_sheets.py
novaposhta/models/__init__.py
novaposhta/schemas/additional_service_general.py
novaposhta/schemas/addresses.py
novaposhta/schemas/common.py
novaposhta/schemas/counterparties.py
novaposhta/schemas/internet_documents.py
novaposhta/schemas/scan_sheets.py
novaposhta/schemas/shared.py
novaposhta/schemas/__init__.py
pynovaposhta-0.2.0.dist-info/RECORD