Metadata-Version: 2.1
Name: pynovaposhta
Version: 0.2.0
Summary: Novaposhta client for humans
Project-URL: Repository, https://gitlab.com/cyberbudy/pynovaposhta/
Author: cyberbudy
Author-email: cyberbudy@gmail.com
License: MIT
Requires-Python: >=3.6
Classifier: Development Status :: 4 - Beta
Classifier: Programming Language :: Python :: 3
Classifier: Intended Audience :: Developers
Classifier: Topic :: Utilities
Classifier: License :: OSI Approved :: MIT License
Classifier: Operating System :: OS Independent
Requires-Dist: coverage==5.*,>=5.3.1; extra == "dev"
Requires-Dist: flake8==3.*,>=3.8.4; extra == "dev"
Requires-Dist: httpx==0.*,>=0.16.1
Requires-Dist: ipython==7.*,>=7.19.0; extra == "dev"
Requires-Dist: mypy==0.*,>=0.790.0; extra == "dev"
Requires-Dist: pydantic==1.*,>=1.7.3
Requires-Dist: pyhumps==1.*,>=1.6.1
Requires-Dist: pytest==6.*,>=6.2.1; extra == "dev"
Requires-Dist: pytest-cov==2.*,>=2.10.1; extra == "dev"
Provides-Extra: dev
